{
  "slug": "post-essential-tips-for-ac-maintenance-before-summer-starts",
  "route": "/blog/essential-ac-maintenance-tips-before-summer/",
  "cat": "blog",
  "title": "Essential Tips for AC Maintenance Before Summer Starts",
  "desc": "MISSING",
  "h1": "",
  "wordcount": 814,
  "body": "Search\n\n\\\n\n![](https://static.wixstatic.com/media/824e75_f23952109f494e6d8db7b7263243b072~mv2.jpg/v1/fill/w_740,h_740,al_c,q_85,usm_0.66_1.00_0.01,enc_avif,quality_auto/824e75_f23952109f494e6d8db7b7263243b072~mv2.jpg)\n\nSummer heat can be relentless, and a well-functioning air conditioner is key to staying comfortable indoors. Many people wait until the temperature soars before checking their AC units, but this often leads to unexpected breakdowns and costly repairs. Preparing your air conditioner before summer begins ensures it runs efficiently, saves energy, and extends its lifespan. This guide offers practical tips to help you maintain your AC system and avoid discomfort during the hottest months.\n\n\\\n\n## Check and Replace Air Filters\n\n\\\n\nOne of the simplest yet most effective maintenance tasks is inspecting the air filters. Dirty or clogged filters reduce airflow, forcing the AC to work harder and consume more energy. This can also lower indoor air quality.\n\n\\\n\n- Locate your AC’s air filter, usually behind the front grille or inside the blower compartment.\n\n- Remove the filter and inspect it for dust, dirt, and debris.\n\n- Replace disposable filters every 1 to 3 months, depending on usage and air quality.\n\n- If you have a reusable filter, clean it with water and mild detergent, then let it dry completely before reinstalling.\n\n  \\\n\nRegular filter maintenance improves airflow, reduces strain on the system, and helps keep your home’s air fresh.\n\n\\\n\n## Clean the Coils and Fins\n\n\\\n\nThe evaporator and condenser coils play a crucial role in cooling air. Over time, these coils collect dirt and dust, which reduces their ability to absorb heat. This makes the AC less efficient and can cause it to overheat.\n\n\\\n\n- Turn off the power to the unit before cleaning.\n\n- Use a soft brush or vacuum with a brush attachment to gently remove dirt from the coils.\n\n- Straighten any bent fins with a fin comb to maintain proper airflow.\n\n- For outdoor condenser units, clear away leaves, grass, and other debris around the unit.\n\n  \\\n\nKeeping coils clean helps your AC cool more effectively and lowers energy bills.\n\n\\\n\n## Inspect the Drain Line\n\n\\\n\nThe drain line removes condensation produced by the air conditioner. If it becomes clogged, water can back up and cause leaks or damage.\n\n\\\n\n- Locate the drain line near the indoor unit.\n\n- Use a wet/dry vacuum to clear any blockages.\n\n- Pour a cup of white vinegar or a mild bleach solution down the drain to prevent mold and algae buildup.\n\n- Check that the drain line is properly sloped to allow water to flow freely.\n\n  \\\n\nRegular drain line maintenance prevents water damage and keeps your AC running smoothly.\n\n\\\n\n## Test the Thermostat\n\n\\\n\nA malfunctioning thermostat can cause your AC to run inefficiently or not at all. Testing it before summer helps avoid unexpected problems.\n\n\\\n\n- Set the thermostat to cooling mode and lower the temperature below the current room temperature.\n\n- Listen for the AC to turn on and check if cool air starts flowing within a few minutes.\n\n- If your thermostat is old or inaccurate, consider upgrading to a programmable or smart thermostat for better control and energy savings.\n\n  \\\n\nProper thermostat function ensures your home stays comfortable without wasting energy.\n\n\\\n\n## Check Refrigerant Levels\n\n\\\n\nRefrigerant is the substance that cools the air inside your home. Low refrigerant levels can reduce cooling performance and damage the compressor.\n\n\\\n\n- Signs of low refrigerant include weak airflow, warm air blowing from vents, or ice buildup on coils.\n\n- Only a licensed HVAC technician should check and recharge refrigerant due to safety and environmental regulations.\n\n- Schedule a professional inspection if you notice any of these symptoms or if your AC hasn’t been serviced in over a year.\n\n  \\\n\nMaintaining correct refrigerant levels keeps your AC efficient and prevents costly repairs.\n\n\\\n\n## Inspect Electrical Components\n\n\\\n\nElectrical issues can cause your AC to fail or operate unsafely. Checking wiring and connections helps identify problems early.\n\n\\\n\n- Turn off power to the unit before inspection.\n\n- Look for signs of wear, corrosion, or loose connections on wires and terminals.\n\n- Listen for unusual noises like buzzing or clicking when the unit runs.\n\n- If you notice any issues, call a professional electrician or HVAC technician.\n\n  \\\n\nRegular electrical inspections improve safety and reliability.\n\n\\\n\n## Clear the Area Around the Outdoor Unit\n\n\\\n\nThe outdoor condenser unit needs plenty of space for airflow. Obstructions can reduce efficiency and cause overheating.\n\n\\\n\n- Remove plants, weeds, and debris within at least two feet of the unit.\n\n- Trim back any branches or shrubs that block airflow.\n\n- Avoid placing objects like furniture or grills near the unit.\n\n  \\\n\nA clear area around the condenser helps your AC cool effectively and prevents damage.\n\n\\\n\n## Schedule Professional Maintenance\n\n\\\n\nEven with regular DIY care, a professional tune-up once a year is essential. HVAC technicians perform thorough inspections, cleanings, and repairs that go beyond basic maintenance.\n\n\\\n\n- They check refrigerant levels, electrical components, and system performance.\n\n- They can identify and fix small issues before they become major problems.\n\n- Professional service improves efficiency, extends equipment life, and ensures safety.\n\n  \\\n\nBook a maintenance appointment before summer to keep your AC in top shape.\n\n\\\n\n[](https://www.quickfast.ca/post/why-you-should-schedule-your-ac-installation-today)\n\n![Why You Should Schedule Your AC Installation Today](https://static.wixstatic.com/media/824e75_97cb345fbcff45079e7135d9fecad002~mv2.jpg/v1/fill/w_289,h_162,al_c,q_80,usm_0.66_1.00_0.01,enc_avif,quality_auto/824e75_97cb345fbcff45079e7135d9fecad002~mv2.jpg)\n\n[](https://www.quickfast.ca/post/10-benefits-of-choosing-quickfast-for-your-ac-installation)\n\n![10 Benefits of Choosing QuickFast for Your AC Installation](https://static.wixstatic.com/media/11062b_2d67360dd0a5444d8a68715ea132356f~mv2.jpeg/v1/fill/w_289,h_162,al_c,q_80,usm_0.66_1.00_0.01,enc_avif,quality_auto/11062b_2d67360dd0a5444d8a68715ea132356f~mv2.jpeg)\n\nGet in Touch"
}